many_requests_cli/__init__.py
many_requests_cli/main.py
many_requests_cli-0.1.2.dist-info/entry_points.txt
many_requests_cli-0.1.2.dist-info/WHEEL
many_requests_cli-0.1.2.dist-info/METADATA
many_requests_cli-0.1.2.dist-info/RECORD
